{"turn":1,"table":{"pos4":{"number":"6","color":"spades"},"pos3":null,"pos2":null,"pos1":null},"round":4,"players":["pl_1","pl_2","pl_3","pl_4"],"onTurnPlayer":"pl_1","groups":[{"wonCards":[],"points":0,"players":["pl_3","pl_1"]},{"wonCards":[[{"number":"queen","color":"hearts"},{"number":"8","color":"hearts"},{"number":"6","color":"clubs"},{"number":"ace","color":"hearts"}],[{"number":"10","color":"diamonds"},{"number":"7","color":"clubs"},{"number":"8","color":"spades"},{"number":"ace","color":"diamonds"}],[{"number":"queen","color":"diamonds"},{"number":"7","color":"diamonds"},{"number":"7","color":"spades"},{"number":"9","color":"diamonds"}],[{"number":"8","color":"diamonds"},{"number":"jack","color":"diamonds"},{"number":"7","color":"hearts"},{"number":"6","color":"diamonds"}]],"points":72,"players":["pl_4","pl_2"]}],"game_id":"0","gameType":"diamonds","cards":{"pl_4":[{"number":"6","color":"hearts"},{"number":"queen","color":"spades"},{"number":"king","color":"spades"},{"number":"king","color":"diamonds"}],"pl_3":[{"number":"9","color":"spades"},{"number":"ace","color":"spades"},{"number":"9","color":"clubs"},{"number":"10","color":"clubs"},{"number":"queen","color":"clubs"}],"pl_2":[{"number":"9","color":"hearts"},{"number":"jack","color":"hearts"},{"number":"jack","color":"spades"},{"number":"8","color":"clubs"},{"number":"king","color":"clubs"}],"pl_1":[{"number":"10","color":"hearts"},{"number":"king","color":"hearts"},{"number":"10","color":"spades"},{"number":"jack","color":"clubs"},{"number":"ace","color":"clubs"}]}}